LICENSE
MANIFEST.in
README.md
changelog
setup.py
sgejob/__init__.py
sgejob/daemon.py
sgejob/sgejob.py
sgejob.egg-info/PKG-INFO
sgejob.egg-info/SOURCES.txt
sgejob.egg-info/dependency_links.txt
sgejob.egg-info/entry_points.txt
sgejob.egg-info/requires.txt
sgejob.egg-info/top_level.txt