Metadata-Version: 2.1
Name: sgejob
Version: 0.0.8
Summary: To collect SGE job information with a damemon
Home-page: https://github.com/linzhi2013
Author: Guanliang MENG
Author-email: mengguanliang@foxmail.com
License: UNKNOWN
Platform: UNKNOWN
Classifier: Development Status :: 3 - Alpha
Classifier: Intended Audience :: Science/Research
Classifier: Topic :: Scientific/Engineering :: Bio-Informatics
Classifier: License :: OSI Approved :: GNU General Public License v3 or later (GPLv3+)
Classifier: Programming Language :: Python :: 3
Classifier: Operating System :: POSIX :: Linux
Requires-Python: >=3
